MANIFEST.in
README.rst
setup.cfg
setup.py
timeseriesprocessing/__init__.py
timeseriesprocessing/constants.py
timeseriesprocessing/timeSeriesDataFrame.py
timeseriesprocessing/utilities.py
timeseriesprocessing.egg-info/PKG-INFO
timeseriesprocessing.egg-info/SOURCES.txt
timeseriesprocessing.egg-info/dependency_links.txt
timeseriesprocessing.egg-info/requires.txt
timeseriesprocessing.egg-info/top_level.txt