Metadata-Version: 1.1
Name: timeseriesprocessing
Version: 0.0.1
Summary: Time Series Processing Using Regression
Home-page: https://github.com/george-j-zhu/timeseriesprocessing
Author: Jiajun Zhu
Author-email: george.choo@outlook.com
License: UNKNOWN
Keywords: Time Series Processing Using Regression
Platform: UNKNOWN
Classifier: Development Status :: 3 - Alpha
Classifier: Intended Audience :: Developers
Classifier: Topic :: Scientific/Engineering :: Artificial Intelligence
Classifier: License :: OSI Approved :: MIT License
Classifier: Programming Language :: Python :: 3.4
Classifier: Programming Language :: Python :: 3.5
Classifier: Programming Language :: Python :: 3.6
